oidc_drf/__init__.py
oidc_drf/admin.py
oidc_drf/backends.py
oidc_drf/drf.py
oidc_drf/models.py
oidc_drf/urls.py
oidc_drf/utils.py
oidc_drf/views.py
oidc_drf/migrations/0001_initial.py
oidc_drf/migrations/__init__.py
oidc_drf-1.3.5.dist-info/METADATA
oidc_drf-1.3.5.dist-info/WHEEL
oidc_drf-1.3.5.dist-info/top_level.txt
oidc_drf-1.3.5.dist-info/RECORD
